odoo/addons/website_snippet_preset/README.rst
odoo/addons/website_snippet_preset/__init__.py
odoo/addons/website_snippet_preset/__manifest__.py
odoo/addons/website_snippet_preset/models/__init__.py
odoo/addons/website_snippet_preset/models/snippet_preset.py
odoo/addons/website_snippet_preset/security/ir.model.access.csv
odoo/addons/website_snippet_preset/static/src/css/website_snippet_preset.css
odoo/addons/website_snippet_preset/static/src/js/website_snippet_preset.js
odoo/addons/website_snippet_preset/static/src/xml/website_snippet_preset.xml
odoo/addons/website_snippet_preset/templates/assets.xml
odoo11_addon_website_snippet_preset-11.0.1.0.0.dist-info/DESCRIPTION.rst
odoo11_addon_website_snippet_preset-11.0.1.0.0.dist-info/METADATA
odoo11_addon_website_snippet_preset-11.0.1.0.0.dist-info/RECORD
odoo11_addon_website_snippet_preset-11.0.1.0.0.dist-info/WHEEL
odoo11_addon_website_snippet_preset-11.0.1.0.0.dist-info/metadata.json
odoo11_addon_website_snippet_preset-11.0.1.0.0.dist-info/top_level.txt
